{
    "lastSentInfo": {
        "lastSentTime": "2025-07-08 12:02:13"
    },
    "weatherData": {
        "lastSentTime": "2025-07-08 12:02:13",
        "phenomena": "大豪雨",
        "location": [
            "彰化縣"
        ],
        "issueTime": "2025-07-08 11:55:00",
        "update": "2025-07-08 11:59:56"
    },
    "lastMessage": "⚠️ 最新大豪雨特報 ⚠️\n對流雲系發展旺盛，易有短延時強降雨，今（８）日彰化縣有局部豪雨或大豪雨，南投縣、雲林縣地區及嘉義縣、高雄市山區有局部大雨或豪雨，中南部地區有局部大雨發生的機率；請注意雷擊及強陣風，山區嚴防坍方、落石、土石流及溪水暴漲，低窪地區請慎防積淹水。\n\n大豪雨地區：彰化縣。\n\n特報發佈時間：2025-07-08 11:59:56\n\n📍 大豪雨特報地區：\n彰化縣\n\n⚠️ 最新豪雨特報 ⚠️\n對流雲系發展旺盛，易有短延時強降雨，今（８）日彰化縣有局部豪雨或大豪雨，南投縣、雲林縣地區及嘉義縣、高雄市山區有局部大雨或豪雨，中南部地區有局部大雨發生的機率；請注意雷擊及強陣風，山區嚴防坍方、落石、土石流及溪水暴漲，低窪地區請慎防積淹水。\n\n大豪雨地區：彰化縣。\n\n特報發佈時間：2025-07-08 11:59:56\n\n📍 豪雨特報地區：\n南投縣\n雲林縣\n嘉義縣山區\n高雄市山區\n\n⚠️ 最新大雨特報 ⚠️\n對流雲系發展旺盛，易有短延時強降雨，今（８）日彰化縣有局部豪雨或大豪雨，南投縣、雲林縣地區及嘉義縣、高雄市山區有局部大雨或豪雨，中南部地區有局部大雨發生的機率；請注意雷擊及強陣風，山區嚴防坍方、落石、土石流及溪水暴漲，低窪地區請慎防積淹水。\n\n大豪雨地區：彰化縣。\n\n特報發佈時間：2025-07-08 11:59:56\n\n📍 大雨特報地區：\n臺中市\n嘉義市\n嘉義縣\n臺南市\n高雄市\n屏東縣\n恆春半島\n\n當地1小時/3小時/24小時累積雨量\n南投縣 南投市 六分寮 74.0mm/91.5mm/106.5mm\n臺中市 新社區 頭櫃山 4.5mm/25.5mm/75.5mm\n嘉義縣 竹崎鄉 石磐龍 1.5mm/1.5mm/86.0mm\n嘉義市 東區 嘉義市東區 5.5mm/7.5mm/18.5mm\n臺南市 南化區 大竹坑 1.0mm/1.0mm/93.0mm\n高雄市 茂林區 多納林道 0.0mm/2.0mm/147.5mm\n屏東縣 春日鄉 大漢山 0.5mm/2.5mm/147.0mm\n彰化縣 福興鄉 福興 24.5mm/227.0mm/245.0mm\n雲林縣 西螺鎮 西螺 78.5mm/79.5mm/82.5mm"
}