{
    "lastSentInfo": {
        "lastSentTime": "2025-06-14 04:37:10"
    },
    "weatherData": {
        "lastSentTime": "2025-06-14 04:37:10",
        "phenomena": "豪雨",
        "location": [
            "高雄市",
            "屏東縣"
        ],
        "issueTime": "2025-06-14 03:35:00",
        "update": "2025-06-14 04:35:27"
    },
    "lastMessage": "⚠️ 最新豪雨特報 ⚠️\n低壓帶及西南風影響，易有短延時強降雨，今（１４）日高雄市、屏東縣有局部大雨或豪雨，嘉義、臺南地區、蘭嶼、綠島、恆春半島及臺東山區有局部大雨發生的機率，請注意雷擊及強陣風；連日降雨，山區請嚴防坍方、落石、土石流及溪水暴漲，低窪地區請慎防積水。\n\n特報發佈時間：2025-06-14 04:35:27\n\n📍 豪雨特報地區：\n高雄市\n屏東縣\n\n⚠️ 最新大雨特報 ⚠️\n低壓帶及西南風影響，易有短延時強降雨，今（１４）日高雄市、屏東縣有局部大雨或豪雨，嘉義、臺南地區、蘭嶼、綠島、恆春半島及臺東山區有局部大雨發生的機率，請注意雷擊及強陣風；連日降雨，山區請嚴防坍方、落石、土石流及溪水暴漲，低窪地區請慎防積水。\n\n特報發佈時間：2025-06-14 04:35:27\n\n📍 大雨特報地區：\n嘉義市\n嘉義縣\n臺南市\n恆春半島\n臺東縣山區\n蘭嶼綠島\n\n當地1小時/3小時/24小時累積雨量\n嘉義縣 阿里山鄉 里佳 0.0mm/0.0mm/168.5mm\n嘉義市 西區 嘉義 0.0mm/0.0mm/132.5mm\n臺南市 南化區 羌黃坑 0.5mm/0.5mm/167.0mm\n高雄市 六龜區 六龜 2.0mm/3.0mm/285.0mm\n屏東縣 春日鄉 大漢山 5.0mm/25.5mm/276.0mm\n臺東縣 達仁鄉 達仁林場 0.0mm/1.5mm/127.5mm"
}